showfile/__init__.py
showfile/main.py
showfile/theme.py
showfile-0.1.2.dist-info/LICENSE
showfile-0.1.2.dist-info/METADATA
showfile-0.1.2.dist-info/WHEEL
showfile-0.1.2.dist-info/entry_points.txt
showfile-0.1.2.dist-info/top_level.txt
showfile-0.1.2.dist-info/RECORD
