Metadata-Version: 2.1
Name: showfile
Version: 0.1.2
Summary: A tool to view files with their proper syntax highlighting in the console
Home-page: https://wasi-master.github.io/showfile/
Author: Wasi Master
Author-email: arianmollik323@gmail.com
License: MIT
Project-URL: Github, https://github.com/wasi-master/showfile
Project-URL: Bug Tracker, https://github.com/wasi-master/showfile/issues
Project-URL: Documentation, https://github.com/wasi-master/showfile/blob/main/README.md
Project-URL: Say Thanks, https://saythanks.io/to/arianmollik323@gmail.com
Platform: UNKNOWN
Classifier: Programming Language :: Python :: 3.6
Classifier: Programming Language :: Python :: 3.7
Classifier: Programming Language :: Python :: 3.8
Classifier: Programming Language :: Python :: 3.9
Classifier: Programming Language :: Python :: 3.10
Classifier: License :: OSI Approved :: MIT License
Classifier: Operating System :: OS Independent
Classifier: Development Status :: 4 - Beta
Classifier: Environment :: Console
Classifier: Intended Audience :: Developers
Classifier: Intended Audience :: End Users/Desktop
Classifier: Natural Language :: English
Classifier: Topic :: Terminals
Classifier: Topic :: Text Processing
Classifier: Topic :: Text Processing :: General
Requires-Python: >=3.6
Requires-Dist: rich
